tox_auto_env.py
tox_auto_env-0.0.8.dist-info/LICENSE.md
tox_auto_env-0.0.8.dist-info/METADATA
tox_auto_env-0.0.8.dist-info/WHEEL
tox_auto_env-0.0.8.dist-info/entry_points.txt
tox_auto_env-0.0.8.dist-info/top_level.txt
tox_auto_env-0.0.8.dist-info/RECORD
