Metadata-Version: 2.1
Name: tox-auto-env
Version: 0.0.8
Summary: Keeps your tox virtualenv always up to date with dependencies
Home-page: https://github.com/ramshaw888/tox-auto-env
Author: Aaron Ramshaw
License: UNKNOWN
Platform: UNKNOWN
Classifier: Framework :: tox
